search_query/__init__.py
search_query/__version__.py
search_query/cli.py
search_query/constants.py
search_query/database.py
search_query/database_queries.py
search_query/exception.py
search_query/linter.py
search_query/linter_base.py
search_query/parser.py
search_query/parser_base.py
search_query/query.py
search_query/query_and.py
search_query/query_near.py
search_query/query_not.py
search_query/query_or.py
search_query/query_range.py
search_query/query_term.py
search_query/registry.py
search_query/search_file.py
search_query/serializer_base.py
search_query/serializer_structured.py
search_query/translator_base.py
search_query/upgrade.py
search_query/utils.py
search_query/ebscohost/__init__.py
search_query/ebscohost/constants.py
search_query/ebscohost/linter.py
search_query/ebscohost/parser.py
search_query/ebscohost/serializer.py
search_query/ebscohost/translator.py
search_query/ebscohost/v_1/__init__.py
search_query/ebscohost/v_1/parser.py
search_query/ebscohost/v_1/serializer.py
search_query/ebscohost/v_1/translator.py
search_query/generic/__init__.py
search_query/generic/linter.py
search_query/generic/serializer.py
search_query/generic/v_1/__init__.py
search_query/generic/v_1/serializer.py
search_query/json_db/ais_senior_scholars_basket.json
search_query/json_db/ais_senior_scholars_list_of_premier_journals.json
search_query/json_db/blocks_bmi_343.json
search_query/json_db/journals_FT50.json
search_query/pre_notation/__init__.py
search_query/pubmed/__init__.py
search_query/pubmed/constants.py
search_query/pubmed/linter.py
search_query/pubmed/parser.py
search_query/pubmed/serializer.py
search_query/pubmed/translator.py
search_query/pubmed/v_1/__init__.py
search_query/pubmed/v_1/parser.py
search_query/pubmed/v_1/serializer.py
search_query/pubmed/v_1/translator.py
search_query/structured/__init__.py
search_query/wos/__init__.py
search_query/wos/constants.py
search_query/wos/linter.py
search_query/wos/parser.py
search_query/wos/serializer.py
search_query-0.13.0.dist-info/METADATA
search_query-0.13.0.dist-info/WHEEL
search_query-0.13.0.dist-info/entry_points.txt
search_query-0.13.0.dist-info/licenses/LICENSE
search_query-0.13.0.dist-info/RECORD
