Metadata-Version: 2.4
Name: search-query
Version: 0.13.0
Summary: Package for managing literature search queries.
Author: Peter Eckhardt, Katharina Ernst, Thomas Fleischmann, Anna Geßler, Karl Schnickmann
Author-email: Gerit Wagner <gerit.wagner@uni-bamberg.de>
License: MIT
License-File: LICENSE
Keywords: literature,literature review,literature search,open science,query translation,reproducible research,research,search query,systematic literature review,systematic review
Classifier: Development Status :: 4 - Beta
Classifier: License :: OSI Approved :: MIT License
Classifier: Natural Language :: English
Classifier: Operating System :: OS Independent
Classifier: Programming Language :: Python :: 3
Classifier: Programming Language :: Python :: 3.8
Classifier: Programming Language :: Python :: 3.9
Classifier: Programming Language :: Python :: 3.10
Classifier: Programming Language :: Python :: 3.11
Classifier: Topic :: Scientific/Engineering
Classifier: Typing :: Typed
Requires-Python: >=3.8
Requires-Dist: importlib-resources>=5.1; python_version < '3.9'
Provides-Extra: dev
Requires-Dist: pre-commit>=3.0.0; extra == 'dev'
Requires-Dist: pylint==3.0.1; extra == 'dev'
Requires-Dist: pytest>=7.2.1; extra == 'dev'
Provides-Extra: docs
Requires-Dist: sphinx-copybutton>=0.5.2; extra == 'docs'
Requires-Dist: sphinx-rtd-theme>=1.1.1; extra == 'docs'
Requires-Dist: sphinx>=5.2.3; extra == 'docs'
Requires-Dist: sphinxcontrib-datatemplates>=0.7; extra == 'docs'
